accesswatch/__init__.py
accesswatch/linux.py
accesswatch/windows.py
accesswatch-1.0.3.dist-info/LICENSE
accesswatch-1.0.3.dist-info/METADATA
accesswatch-1.0.3.dist-info/WHEEL
accesswatch-1.0.3.dist-info/top_level.txt
accesswatch-1.0.3.dist-info/RECORD
