Metadata-Version: 2.1
Name: accesswatch
Version: 1.0.3
Summary: A tool that retrieves and displays file or directory access information In Linux and Windows
Home-page: https://github.com/mahdikhoshdel/accesswatch.git
Author: Mahdi Khoshdel
Author-email: mahdikhoshdel47@gmail.com
License: MIT
Requires-Python: >=3.6
License-File: LICENSE
